Workbook

Sheet Смета
A1: СМ-01. Смета ориентировочная — кв. 108, СПб, вариант D1 (бюджет «Ремонт»)
A2: Цены — ориентировочные для Санкт-Петербурга на 10.2026 (средний сегмент, розница/подрядчики), не являются офертой и подлежат проверке у поставщиков перед закупкой. Материалы — по диапазонам 02-concept/materials.json (price_ref) с поправкой на рост цен 1-го полугодия 2026 (INFOline: плитка +17 %, электрика +15 %, ЛКМ +10 %, напольные +10,5 %); расценки работ — калибровка по открытым прайсам СПб (поиск 2026-10-08, источники в 05-estimate/estimate.md).
A4: Шифр | B4: Этап | C4: Работы, ₽ | D4: Материалы и изделия, ₽ | E4: Итого, ₽ | F4: Доля
A5: Э01 | B5: Демонтаж и подготовка | C5: =SUMIF('Работы'!$A$2:$A$108,A5,'Работы'!$G$2:$G$108) | D5: =SUMIF('Материалы (Ремонт)'!$A$2:$A$275,A5,'Материалы (Ремонт)'!$H$2:$H$275) | E5: =C5+D5 | F5: =E5/$E$19
A6: Э02 | B6: Перегородки, закладки, зашивка окна, каркасные облицовки | C6: =SUMIF('Работы'!$A$2:$A$108,A6,'Работы'!$G$2:$G$108) | D6: =SUMIF('Материалы (Ремонт)'!$A$2:$A$275,A6,'Материалы (Ремонт)'!$H$2:$H$275) | E6: =C6+D6 | F6: =E6/$E$19
A7: Э03 | B7: Утепление и остекление балкона | C7: =SUMIF('Работы'!$A$2:$A$108,A7,'Работы'!$G$2:$G$108) | D7: =SUMIF('Материалы (Ремонт)'!$A$2:$A$275,A7,'Материалы (Ремонт)'!$H$2:$H$275) | E7: =C7+D7 | F7: =E7/$E$19
A8: Э04 | B8: Электромонтаж (черновой), щит, слаботочка, электро-ТП | C8: =SUMIF('Работы'!$A$2:$A$108,A8,'Работы'!$G$2:$G$108) | D8: =SUMIF('Материалы (Ремонт)'!$A$2:$A$275,A8,'Материалы (Ремонт)'!$H$2:$H$275) | E8: =C8+D8 | F8: =E8/$E$19
A9: Э05 | B9: Сантехмонтаж (черновой) и вентиляция | C9: =SUMIF('Работы'!$A$2:$A$108,A9,'Работы'!$G$2:$G$108) | D9: =SUMIF('Материалы (Ремонт)'!$A$2:$A$275,A9,'Материалы (Ремонт)'!$H$2:$H$275) | E9: =C9+D9 | F9: =E9/$E$19
A10: Э06 | B10: Подиум ванной, гидроизоляция, стяжка балкона | C10: =SUMIF('Работы'!$A$2:$A$108,A10,'Работы'!$G$2:$G$108) | D10: =SUMIF('Материалы (Ремонт)'!$A$2:$A$275,A10,'Материалы (Ремонт)'!$H$2:$H$275) | E10: =C10+D10 | F10: =E10/$E$19
A11: Э07 | B11: Штукатурка и шпаклёвка | C11: =SUMIF('Работы'!$A$2:$A$108,A11,'Работы'!$G$2:$G$108) | D11: =SUMIF('Материалы (Ремонт)'!$A$2:$A$275,A11,'Материалы (Ремонт)'!$H$2:$H$275) | E11: =C11+D11 | F11: =E11/$E$19
A12: Э08 | B12: Плиточные работы | C12: =SUMIF('Работы'!$A$2:$A$108,A12,'Работы'!$G$2:$G$108) | D12: =SUMIF('Материалы (Ремонт)'!$A$2:$A$275,A12,'Материалы (Ремонт)'!$H$2:$H$275) | E12: =C12+D12 | F12: =E12/$E$19
A13: Э09 | B13: Потолки ГКЛ, короба, ниши | C13: =SUMIF('Работы'!$A$2:$A$108,A13,'Работы'!$G$2:$G$108) | D13: =SUMIF('Материалы (Ремонт)'!$A$2:$A$275,A13,'Материалы (Ремонт)'!$H$2:$H$275) | E13: =C13+D13 | F13: =E13/$E$19
A14: Э10 | B14: Покраска, молдинги, карнизы, буазери | C14: =SUMIF('Работы'!$A$2:$A$108,A14,'Работы'!$G$2:$G$108) | D14: =SUMIF('Материалы (Ремонт)'!$A$2:$A$275,A14,'Материалы (Ремонт)'!$H$2:$H$275) | E14: =C14+D14 | F14: =E14/$E$19
A15: Э11 | B15: Полы (инженерная доска, LVT) | C15: =SUMIF('Работы'!$A$2:$A$108,A15,'Работы'!$G$2:$G$108) | D15: =SUMIF('Материалы (Ремонт)'!$A$2:$A$275,A15,'Материалы (Ремонт)'!$H$2:$H$275) | E15: =C15+D15 | F15: =E15/$E$19
A16: Э12 | B16: Двери | C16: =SUMIF('Работы'!$A$2:$A$108,A16,'Работы'!$G$2:$G$108) | D16: =SUMIF('Материалы (Ремонт)'!$A$2:$A$275,A16,'Материалы (Ремонт)'!$H$2:$H$275) | E16: =C16+D16 | F16: =E16/$E$19
... A18: Э14 | B18: Вывоз мусора, логистика, уборка | C18: =SUMIF('Работы'!$A$2:$A$108,A18,'Работы'!$G$2:$G$108) | D18: =SUMIF('Материалы (Ремонт)'!$A$2:$A$275,A18,'Материалы (Ремонт)'!$H$2:$H$275) | E18: =C18+D18 | F18: =E18/$E$19
B19: Итого без резерва | C19: =SUM(C5:C18) | D19: =SUM(D5:D18) | E19: =SUM(E5:E18)
B20: Резерв на непредвиденное, % | E20: 0.1
B21: Резерв, ₽ | E21: =E19*E20
B22: ИТОГО «Ремонт» с резервом 10 % | E22: =E19+E21

Sheet Работы
A1: Этап | B1: Поз. | C1: Наименование работ | D1: Ед. | E1: Объём | F1: Расценка, ₽ | G1: Сумма, ₽ | H1: Источник объёма (id / лист) | I1: Расчёт
A2: Э01 | B2: Э01.1 | C2: Тепловизионная съёмка пола при работающем водяном ТП, разметка трасс труб | D2: компл | E2: 1 | F2: 14000 | G2: =E2*F2 | H2: planning.json new_walls_general; D3; №13
A3: Э01 | B3: Э01.2 | C3: Укрытие и защита стяжки с водяным ТП на период работ | D3: м² | E3: 61.7 | F3: 120 | G3: =E3*F3 | H3: planning.json areas.sum_without_balcony
A4: Э01 | B4: Э01.3 | C4: Демонтаж заполнения балконного проёма O4 (блок, порог), без расширения проёма | D4: шт | E4: 1 | F4: 9000 | G4: =E4*F4 | H4: O4-fill; D2; АР-05
A5: Э01 | B5: Э01.4 | C5: Пробивка проёмов в перегородках W12 (D3) и W11 (D4) вручную, без ударного инструмента | D5: м² | E5: 1.35 | F5: 4500 | G5: =E5*F5 | H5: W12-cut, W11-cut; АР-05 | I5: W12 0.61 + W11 0.74
A6: Э01 | B6: Э01.5 | C6: Демонтаж подоконной доски и внутренних откосов O1 | D6: шт | E6: 1 | F6: 2500 | G6: =E6*F6 | H6: O1-infill; АР-05
A7: Э01 | B7: Э01.6 | C7: Демонтаж приборов застройщика (WC постирочной F1 и пр., если установлены), заглушки | D7: компл | E7: 1 | F7: 6000 | G7: =E7*F7 | H7: planning demolition F1, F-all
A8: Э02 | B8: Э02.1 | C8: Кладка ПГП 100 на клей по демпферной ленте (NW1, закладка O9) + ГКЛ на клей со стороны кухни | D8: м² | E8: 4.87 | F8: 2600 | G8: =E8*F8 | H8: NW1; АР-06
A9: Э02 | B9: Э02.2 | C9: Кладка ПГП 80 (NW4 за вычетом проёма D2, добор у D1) | D9: м² | E9: 2.2 | F9: 1700 | G9: =E9*F9 | H9: NW4; elevations R1 W7 добор 199
A10: Э02 | B10: Э02.3 | C10: Кладка ПГП-Г 80 (закладки NW8, NW9) с обмазочной ГИ со стороны с/у | D10: м² | E10: 2.14 | F10: 1900 | G10: =E10*F10 | H10: NW8, NW9
A11: Э02 | B11: Э02.4 | C11: Устройство перемычек над новыми проёмами D3, D4 | D11: шт | E11: 2 | F11: 2000 | G11: =E11*F11 | H11: W12-cut, W11-cut
A12: Э02 | B12: Э02.5 | C12: Зашивка окна O1 изнутри: каркас в откосе, минвата, пароизоляция, 2×ГКЛ (съёмная зона под буазери) | D12: м² | E12: 2.98 | F12: 5000 | G12: =E12*F12 | H12: window_infill O1; узел 8
A13: Э02 | B13: Э02.6 | C13: Облицовка W7 ГКЛ 12,5 на профиле (без штроб в ж/б, D15, D23) | D13: м² | E13: 11.05 | F13: 1100 | G13: =E13*F13 | H13: walls R1 gkl_cladding; АР-15
A14: Э02 | B14: Э02.7 | C14: Облицовка W14 в душе VK-C1: каркас + 2×ГВЛВ, к стене и потолку (без крепления в пол), ниши 2 шт | D14: м² | E14: 2.29 | F14: 3500 | G14: =E14*F14 | H14: VK-C1; узел 11
A15: Э02 | B15: Э02.8 | C15: Короб инсталляции с полкой h 1200 (2×ГВЛВ) | D15: шт | E15: 1 | F15: 6500 | G15: =E15*F15 | H15: F69; АР-13
A16: Э02 | B16: Э02.9 | C16: Короб-перемычка VK-C2 h 450 и экран ванны на каркасе с ревизией H6 | D16: м² | E16: 1.68 | F16: 3000 | G16: =E16*F16 | H16: VK-C2; экран ванны; H6
A17: Э02 | B17: Э02.10 | C17: Закладные под люстры, подвесы, проектор, ДСК, сушилку, карниз с приводом | D17: шт | E17: 7 | F17: 1500 | G17: =E17*F17 | H17: finish-quantities counts
... A23: Э04 | B23: Э04.2 | C23: Сборка щита: установка и расключение модульных аппаратов, маркировка | D23: модуль | E23: 32 | F23: 1000 | G23: =E23*F23 | H23: panel.json modules_used
A24: Э04 | B24: Э04.3 | C24: Прокладка силового кабеля в гофре по потолку (с креплением) | D24: м | E24: 681.49 | F24: 110 | G24: =E24*F24 | H24: panel.json Σ length_m × 1,15 | I24: 592.6 × 1,15
A25: Э04 | B25: Э04.4 | C25: Прокладка слаботочных кабелей (Cat6, RG-6, акустика, датчики, краны, AV) | D25: м | E25: 186.02 | F25: 110 | G25: =E25*F25 | H25: electrical.json low_voltage (трассы по координатам)
A26: Э04 | B26: Э04.5 | C26: Штробление вертикальное ≤ 25 мм (кирпич) с заделкой / спуски в облицовках | D26: м | E26: 119.83 | F26: 600 | G26: =E26*F26 | H26: sockets + switches: (потолок − h) | I26: Σ спусков к точкам
A27: Э04 | B27: Э04.6 | C27: Установка подрозетника (высверливание в кирпиче/ГКЛ), монтаж точки | D27: шт | E27: 87 | F27: 550 | G27: =E27*F27 | H27: посты sockets + switches
A28: Э04 | B28: Э04.7 | C28: Вывод под светильник / ленту (кабель, коробка, маркировка) | D28: шт | E28: 42 | F28: 450 | G28: =E28*F28 | H28: electrical.json lights
A29: Э04 | B29: Э04.8 | C29: Укладка нагревательных матов в клей с датчиком пола (TP1–TP3) | D29: м² | E29: 5.27 | F29: 1300 | G29: =E29*F29 | H29: heating.json; ОВ-01
A30: Э04 | B30: Э04.9 | C30: ДУП ванной и постирочной (КУП, ПуГВ 4 мм²) | D30: шт | E30: 2 | F30: 3500 | G30: =E30*F30 | H30: panel.json rcd_policy
A31: Э04 | B31: Э04.10 | C31: Монтаж СС-щита U16, расшивка патч-панели, тестирование линий | D31: компл | E31: 1 | F31: 9000 | G31: =E31*F31 | H31: U16; LV00
A32: Э04 | B32: Э04.11 | C32: Электролаборатория: измерения, протокол | D32: компл | E32: 1 | F32: 15000 | G32: =E32*F32 | H32: ЭМ-03
A33: Э05 | B33: Э05.1 | C33: Сборка узла ввода (краны, фильтр-редуктор, счётчики, обр. клапан, электрокраны, коллекторы) | D33: узел | E33: 2 | F33: 16000 | G33: =E33*F33 | H33: N1, N2; ВК-03
A34: Э05 | B34: Э05.2 | C34: Разводка водоснабжения PEX-a до водорозетки (трасса + вывод) | D34: вывод | E34: 12 | F34: 3200 | G34: =E34*F34 | H34: pipes.water WB1–WL2
A35: Э05 | B35: Э05.3 | C35: Разводка канализации ПП к прибору с уклоном (трасса + вывод) | D35: вывод | E35: 7 | F35: 2900 | G35: =E35*F35 | H35: pipes.sewer S1–S7; calc_sewer_slopes.py
A36: Э05 | B36: Э05.4 | C36: Монтаж инсталляции (рама к стене, D3) | D36: шт | E36: 1 | F36: 7000 | G36: =E36*F36 | H36: F69; P01
A37: Э05 | B37: Э05.5 | C37: Монтаж линейного трапа низкого (h ≤ 70) с фланцем | D37: шт | E37: 1 | F37: 7500 | G37: =E37*F37 | H37: F67; S1; узел 7
A38: Э05 | B38: Э05.6 | C38: Монтаж скрытой части термостата душа в облицовке VK-C1 | D38: шт | E38: 1 | F38: 6000 | G38: =E38*F38 | H38: P04; WB3
... A43: Э05 | B43: Э05.11 | C43: Алмазное бурение Ø132 в наружной стене 420 под бризеры | D43: шт | E43: 2 | F43: 6500 | G43: =E43*F43 | H43: BR1, BR2
A44: Э06 | B44: Э06.1 | C44: Гидроизоляция обмазочная 2 слоя с лентами (пол R5 — нижняя + основная, пол R6, стены) | D44: м² | E44: 26.56 | F44: 1000 | G44: =E44*F44 | H44: floors waterproofing_floor; waterproofing_walls | I44: R5 5.17×2 + R6 3.12 + стены 13.1
A45: Э06 | B45: Э06.2 | C45: Подиум ванной ЦПС 78,5 мм армированный, уклон 1,5 % к трапу | D45: м² | E45: 5.1 | F45: 2500 | G45: =E45*F45 | H45: floors podium_screed_80; D18
A46: Э06 | B46: Э06.3 | C46: Рамка-бортик коллектора U14 | D46: шт | E46: 1 | F46: 4000 | G46: =E46*F46 | H46: VK-C3; узел 6
A47: Э06 | B47: Э06.4 | C47: Пол балкона: ремонт плиты, XPS 50, ПЭ-плёнка, демпферная лента | D47: м² | E47: 6.86 | F47: 900 | G47: =E47*F47 | H47: P-BALC; D22
A48: Э06 | B48: Э06.5 | C48: Стяжка балкона ЦПС 55 армированная + СВС 10 по мату TP3 | D48: м² | E48: 6.86 | F48: 1900 | G48: =E48*F48 | H48: P-BALC
A49: Э07 | B49: Э07.1 | C49: Штукатурка стен по маякам (гипсовая), ср. 15 мм | D49: м² | E49: 118.4 | F49: 750 | G49: =E49*F49 | H49: walls (gross − проёмы, без облицовок)
A50: Э07 | B50: Э07.2 | C50: Штукатурка стен по маякам (цементная, влажные помещения) | D50: м² | E50: 33.89 | F50: 850 | G50: =E50*F50 | H50: walls R5, R6
A51: Э07 | B51: Э07.3 | C51: Откосы: штукатурка, уголок, шпаклёвка (O2, O3, портал O4) | D51: м² | E51: 5.38 | F51: 2200 | G51: =E51*F51 | H51: walls plaster+paint*
A52: Э07 | B52: Э07.4 | C52: Шпаклёвка стен Q3 под покраску + стеклохолст-паутинка | D52: м² | E52: 105.6 | F52: 1100 | G52: =E52*F52 | H52: walls net (окрашиваемые)
A53: Э07 | B53: Э07.5 | C53: Шпаклёвка Q2 + грунт за встроенной мебелью и кухней | D53: м² | E53: 50.01 | F53: 350 | G53: =E53*F53 | H53: walls behind_furniture + paint_q2
A54: Э07 | B54: Э07.6 | C54: Шпаклёвка потолков и коробов ГКЛ Q4 (швы + сплошная) | D54: м² | E54: 69.3 | F54: 950 | G54: =E54*F54 | H54: ceilings Σ
A55: Э08 | B55: Э08.1 | C55: Укладка керамогранита 60×60 на пол (прихожая, ванная, постирочная) | D55: м² | E55: 7.74 | F55: 2800 | G55: =E55*F55 | H55: floors porcelain_60x60_*
A56: Э08 | B56: Э08.2 | C56: Укладка керамогранита 60×120 на пол душа с уклоном к трапу | D56: м² | E56: 0.71 | F56: 4800 | G56: =E56*F56 | H56: floors porcelain_60x120_shower
... A70: Э09 | B70: Э09.7 | C70: Люки потолочные HC-1, вентрешётка HC-2 | D70: шт | E70: 2 | F70: 3000 | G70: =E70*F70 | H70: HC-1, HC-2
A71: Э10 | B71: Э10.1 | C71: Окраска стены, матовая моющаяся класс 1–2 (C2), 2 слоя | D71: м² | E71: 56.72 | F71: 550 | G71: =E71*F71 | H71: finish-quantities; palette.json | I71: R1, R3, R4
A72: Э10 | B72: Э10.2 | C72: Окраска детская, низ до +900, износостойкая класс 1 (C5), 2 слоя | D72: м² | E72: 9.02 | F72: 650 | G72: =E72*F72 | H72: finish-quantities; palette.json | I72: R2
A73: Э10 | B73: Э10.3 | C73: Окраска детская, верх стен (C1), 2 слоя | D73: м² | E73: 18.04 | F73: 550 | G73: =E73*F73 | H73: finish-quantities; palette.json | I73: R2
A74: Э10 | B74: Э10.4 | C74: Окраска стены ванной/постирочной, для влажных помещений (C2), 2 слоя | D74: м² | E74: 11.42 | F74: 550 | G74: =E74*F74 | H74: finish-quantities; palette.json | I74: R5, R6
A75: Э10 | B75: Э10.5 | C75: Окраска балкон, глубокоматовая, тёмная (3 слоя) (C6), 3 слоя | D75: м² | E75: 10.4 | F75: 750 | G75: =E75*F75 | H75: finish-quantities; palette.json | I75: R7
A76: Э10 | B76: Э10.6 | C76: Окраска откосы O2, O3, портал O4 (C1), 2 слоя | D76: м² | E76: 5.38 | F76: 550 | G76: =E76*F76 | H76: finish-quantities; palette.json | I76: R1, R2, R3
A77: Э10 | B77: Э10.7 | C77: Окраска потолки ГКЛ, глубокоматовая (C1), 2 слоя | D77: м² | E77: 54.93 | F77: 550 | G77: =E77*F77 | H77: finish-quantities; palette.json | I77: R1, R2, R3, R4
A78: Э10 | B78: Э10.8 | C78: Окраска потолки ГКЛВ ванной и постирочной, влагостойкая (C1), 2 слоя | D78: м² | E78: 8.29 | F78: 550 | G78: =E78*F78 | H78: finish-quantities; palette.json | I78: R5, R6
A79: Э10 | B79: Э10.9 | C79: Окраска потолок балкона и ниша CN-3 (C6), 3 слоя | D79: м² | E79: 6.08 | F79: 750 | G79: =E79*F79 | H79: finish-quantities; palette.json | I79: R7
A80: Э10 | B80: Э10.10 | C80: Монтаж потолочных карнизов (клей, заделка стыков, окраска) | D80: м | E80: 48.37 | F80: 650 | G80: =E80*F80 | H80: linear cornice_*
A81: Э10 | B81: Э10.11 | C81: Монтаж карниза с LED-пазом буазери | D81: м | E81: 2.9 | F81: 1600 | G81: =E81*F81 | H81: linear cornice_boiserie_LED
A82: Э10 | B82: Э10.12 | C82: Монтаж плинтуса МДФ к стене на клею (без крепления в пол), окраска | D82: м | E82: 38.64 | F82: 650 | G82: =E82*F82 | H82: linear plinth_*
A83: Э10 | B83: Э10.13 | C83: Монтаж молдингов (chair rail, рамки R1 W7 и R3 W8) с запилом | D83: м | E83: 34.08 | F83: 800 | G83: =E83*F83 | H83: linear chair_rail; elevations R1 W7; M14
A84: Э11 | B84: Э11.1 | C84: Подготовка основания: шлифовка, обеспыливание, грунт, локальный ремонт; замер влажности CM | D84: м² | E84: 57.92 | F84: 450 | G84: =E84*F84 | H84: P-OAK, P-BALC
A85: Э11 | B85: Э11.2 | C85: Укладка инженерной доски «ёлочка» на клей (без порогов) | D85: м² | E85: 51.45 | F85: 2500 | G85: =E85*F85 | H85: floors oak_herringbone; M01
A86: Э11 | B86: Э11.3 | C86: Укладка LVT «ёлочка» на клей | D86: м² | E86: 6.47 | F86: 1600 | G86: =E86*F86 | H86: floors lvt_herringbone; M28
A87: Э11 | B87: Э11.4 | C87: Стыки покрытий: латунный Т-профиль на клею, пробковые компенсаторы | D87: м | E87: 6.43 | F87: 900 | G87: =E87*F87 | H87: J1, J2, J4
A88: Э12 | B88: Э12.1 | C88: Установка межкомнатной двери (коробка, скрытые петли, фурнитура, наличники с 2 сторон) | D88: шт | E88: 4 | F88: 9500 | G88: =E88*F88 | H88: D1–D4; АР-08
A89: Э12 | B89: Э12.2 | C89: Установка надпроёмной панели D1 и наличника ДВ-1 | D89: шт | E89: 2 | F89: 3500 | G89: =E89*F89 | H89: D1, O5
A90: Э13 | B90: Э13.1 | C90: Установка механизмов розеток/выключателей с рамками | D90: шт | E90: 87 | F90: 350 | G90: =E90*F90 | H90: СП-03.2
A91: Э13 | B91: Э13.2 | C91: Монтаж встраиваемых спотов | D91: шт | E91: 23 | F91: 600 | G91: =E91*F91 | H91: lights type=spot
... A105: Э13 | B105: Э13.16 | C105: Финишная клининговая уборка | D105: м² | E105: 68.5 | F105: 220 | G105: =E105*F105 | H105: planning areas
A106: Э14 | B106: Э14.1 | C106: Вывоз строительного мусора контейнером 8 м³ (норматив 1 конт. на 25 м²) | D106: конт. | E106: 3 | F106: 12000 | G106: =E106*F106 | H106: planning areas | I106: 68.5/25
A107: Э14 | B107: Э14.2 | C107: Погрузка мусора, разгрузка и занос материалов (1 этаж) | D107: компл | E107: 1 | F107: 18000 | G107: =E107*F107 | H107: brief: этаж 1/4
A108: Э14 | B108: Э14.3 | C108: Промежуточные уборки по этапам | D108: компл | E108: 1 | F108: 15000 | G108: =E108*F108 | H108: —
C109: Итого работы | G109: =SUM(G2:G108)

Sheet Материалы (Ремонт)
A1: Этап | B1: Спецификация | C1: Поз. | D1: Наименование | E1: Кол-во | F1: Ед. | G1: Цена, ₽ | H1: Сумма, ₽ | I1: Помещение | J1: Ссылка (лист / id)
A2: Э10 | B2: СП-02.1 | C2: 1 | D2: Буазери стены-изголовья W2 2,9×2,7 м: МДФ 16–19, рамки 25–40, центральная филёнка 1860×1600 съёмная, эмаль C3 | E2: 1 | F2: компл | G2: 95000 | H2: =E2*G2 | I2: R1 | J2: F41; АР-15; M06; узел 8
A3: Э13 | B3: СП-02.1 | C3: 2 | D3: Шкаф-купе Г 2480+745×600 до потолка: корпус ЛДСП E1, двери — рамочный профиль + вставки МДФ эмаль C3 с накладной филёнкой, верхний подвес | E3: 1 | F3: компл | G3: 215000 | H3: =E3*G3 | I3: R1 | J3: F45, F46; M07
A4: Э13 | B4: СП-02.1 | C4: 3 | D4: Шкаф прихожей 2720×600×2650: 3 секции по 900, 6 распашных фасадов МДФ эмаль C2 с рамкой-филёнкой, дверь-зеркало, ниша робота | E4: 1 | F4: компл | G4: 195000 | H4: =E4*G4 | I4: R4 | J4: F60, F61, F62; M17; АР-12
A5: Э13 | B5: СП-02.1 | C5: 4 | D5: Системы хранения постирочной: тумба хозмойки 450, карго 300, столешница компакт-плита 12 мм 770×600, навесные 350, пенал 540, антресоль 650, шкафы 350 у W10 (фасады от пола без дна над U11) | E5: 1 | F5: компл | G5: 115000 | H5: =E5*G5 | I5: R6 | J5: F78, F79, F83, F84, F85, F86, F87, F88; M26; АР-14
A6: Э13 | B6: СП-02.1 | C6: 5 | D6: Сушилка потолочная «лиана» 4 прутка | E6: 1 | F6: шт | G6: 4500 | H6: =E6*G6 | I6: R6 | J6: F89
A7: Э13 | B7: СП-03.1 | C7: 1 | D7: Спот встраиваемый LED 7 Вт, 2700 K, CRI ≥ 90, диммируемый, глубина ≤ 80 — группа L2 | E7: 4 | F7: шт | G7: 2700 | H7: =E7*G7 | I7: R3 | J7: L2-1, L2-2, L2-3, L2-4; ЭО-01
A8: Э13 | B8: СП-03.1 | C8: 2 | D8: Люстра столовой 5–6 рожков LED, латунь сатин/ткань, диммируемая — группа L3 | E8: 1 | F8: шт | G8: 32000 | H8: =E8*G8 | I8: R3 | J8: L3-1; ЭО-01
A9: Э13 | B9: СП-03.1 | C9: 3 | D9: Бра латунь сатин C8 с абажуром — группа L4 | E9: 2 | F9: шт | G9: 9500 | H9: =E9*G9 | I9: R3 | J9: L4-1, L4-2; ЭО-01
A10: Э13 | B10: СП-03.1 | C10: 4 | D10: Спот встраиваемый LED 7 Вт, 2700 K, CRI ≥ 90, диммируемый, глубина ≤ 80 — группа L6 | E10: 4 | F10: шт | G10: 2700 | H10: =E10*G10 | I10: R7 | J10: L6-1, L6-2, L6-3, L6-4; ЭО-01
A11: Э13 | B11: СП-03.1 | C11: 5 | D11: Люстра спальни, диммируемая, латунь/ткань — группа L8 | E11: 1 | F11: шт | G11: 24000 | H11: =E11*G11 | I11: R1 | J11: L8-1; ЭО-01
A12: Э13 | B12: СП-03.1 | C12: 6 | D12: Бра латунь сатин C8 с абажуром — группа L11 | E12: 2 | F12: шт | G12: 9500 | H12: =E12*G12 | I12: R1 | J12: L11-1, L11-2; F41; ЭО-01
A13: Э13 | B13: СП-03.1 | C13: 7 | D13: Светильник потолочный рассеянный детской, диммируемый — группа L14 | E13: 1 | F13: шт | G13: 14000 | H13: =E13*G13 | I13: R2 | J13: L14-1; ЭО-01
... A78: Э04 | B78: СП-03.3 | C78: 12 | D78: Шины N/PE, гребёнки, заглушки, маркировка, DIN-розетки ×3 (P-SS1 в U16) | E78: 1 | F78: компл | G78: 6500 | H78: =E78*G78 | I78: R4 | J78: panel.json; P-SS1
A79: Э04 | B79: СП-03.3 | C79: 13 | D79: Кабель ВВГнг(А)-LS 3×1,5 | E79: =CEILING(240.6*1.15,5) | F79: м | G79: 115 | H79: =E79*G79 | I79: все | J79: C1, C2, C3; panel.json length_m
A80: Э04 | B80: СП-03.3 | C80: 14 | D80: Кабель ВВГнг(А)-LS 3×2,5 | E80: =CEILING(338.8*1.15,5) | F80: м | G80: 170 | H80: =E80*G80 | I80: все | J80: C4, C5, C6, C8, C9, C10, C11, C12, C13, C14, C15, C16, C17, C18, C19, C20, C21, C22; panel.json length_m
A81: Э04 | B81: СП-03.3 | C81: 15 | D81: Кабель ВВГнг(А)-LS 3×6 | E81: =CEILING(13.2*1.15,5) | F81: м | G81: 430 | H81: =E81*G81 | I81: все | J81: C7; panel.json length_m
A82: Э04 | B82: СП-03.3 | C82: 16 | D82: Труба гофрированная ПВХ нг Ø20 с зондом (по потолку, D15) | E82: 700 | F82: м | G82: 28 | H82: =E82*G82 | I82: все | J82: panel.json Σ length_m × 1,15
A83: Э04 | B83: СП-03.3 | C83: 17 | D83: Провод ПуГВ 1×4 + коробки КУП (ДУП ванной и постирочной) | E83: 2 | F83: компл | G83: 1800 | H83: =E83*G83 | I83: R5, R6 | J83: panel.json rcd_policy (ДУП)
A84: Э04 | B84: СП-03.3 | C84: 18 | D84: Крепёж кабеля: клипсы, дюбель-хомуты, распаечные коробки (доступные), клеммы Wago | E84: 1 | F84: компл | G84: 9000 | H84: =E84*G84 | I84: все | J84: 23 групп
A85: Э13 | B85: СП-04 | C85: 1 | D85: Ванна 1700×750 акрил усиленный/кварил, ножки, экран — облицовка плиткой с ревизией H6 | E85: 1 | F85: шт | G85: 42000 | H85: =E85*G85 | I85: R5 | J85: F66; P03; M24
A86: Э13 | B86: СП-04 | C86: 2 | D86: Сифон-автомат ванны с переливом (выпуск у правого торца) | E86: 1 | F86: шт | G86: 6500 | H86: =E86*G86 | I86: R5 | J86: P03; S2
A87: Э13 | B87: СП-04 | C87: 3 | D87: Смеситель для ванны настенный, латунь браш C8 | E87: 1 | F87: шт | G87: 18000 | H87: =E87*G87 | I87: R5 | J87: P03; WB4
A88: Э05 | B88: СП-04 | C88: 4 | D88: Термостат скрытого монтажа на 2 потребителя (встраиваемая часть + лицевая панель), латунь браш | E88: 1 | F88: компл | G88: 38000 | H88: =E88*G88 | I88: R5 | J88: P04; WB3; D23
A89: Э13 | B89: СП-04 | C89: 5 | D89: Верхний душ 250 + кронштейн, ручной душ со шлангом и подключением, латунь браш | E89: 1 | F89: компл | G89: 20000 | H89: =E89*G89 | I89: R5 | J89: P04
A90: Э05 | B90: СП-04 | C90: 6 | D90: Трап линейный низкий 800, h ≤ 70, под плитку, с гидрозатвором и фланцем ГИ | E90: 1 | F90: шт | G90: 16000 | H90: =E90*G90 | I90: R5 | J90: F67; P04; S1; узел 7; D18
A91: Э13 | B91: СП-04 | C91: 7 | D91: Стекло душа фиксированное 315×2000, 8 мм, профиль на клею, стабилизатор к потолку (латунь) | E91: 1 | F91: компл | G91: 22000 | H91: =E91*G91 | I91: R5 | J91: F68
A92: Э05 | B92: СП-04 | C92: 8 | D92: Инсталляция для подвесного унитаза (рама к стене, D3) | E92: 1 | F92: шт | G92: 28000 | H92: =E92*G92 | I92: R5 | J92: F69; P01
A93: Э13 | B93: СП-04 | C93: 9 | D93: Кнопка смыва, латунь браш | E93: 1 | F93: шт | G93: 7000 | H93: =E93*G93 | I93: R5 | J93: F69; P01
... A151: Э12 | B151: СП-02.3 | C151: 27 | D151: Наличник C1 изнутри входной двери ДВ-1 (комплект с цоколем) | E151: 1 | F151: компл | G151: 8000 | H151: =E151*G151 | I151: R4 | J151: O5; ДВ-1
A152: Э11 | B152: СП-05 | C152: 1 | D152: Инженерная доска дуб 2-слойная 14–15 мм, ёлочка 90×600, ультраматовый лак, допуск на водяной ТП | E152: =CEILING(51.45*1.08,1.0) | F152: м² | G152: 7800 | H152: =E152*G152 | I152: R1, R2, R3, R4 | J152: floors oak_herringbone (R1 17,54, R2 11,87, R3 14,59, R4 7,45); M01; АР-10
A153: Э11 | B153: СП-05 | C153: 2 | D153: Клей паркетный MS-полимер эластичный (1,2 кг/м²) | E153: =CEILING(51.45*1.2,15) | F153: кг | G153: 700 | H153: =E153*G153 | I153: R1, R2, R3, R4 | J153: P-OAK; M01
A154: Э11 | B154: СП-05 | C154: 3 | D154: Грунт/ремонтный состав под клей (0,2 л/м²) и локальный ремонт стяжки | E154: 15 | F154: л | G154: 950 | H154: =E154*G154 | I154: R1, R2, R3, R4 | J154: P-OAK
A155: Э11 | B155: СП-05 | C155: 4 | D155: LVT клеевой «ёлочка» в тон дуба C7, 33/42 кл., слой износа ≥ 0,55, допуск на ТП | E155: =CEILING(6.47*1.08,0.5) | F155: м² | G155: 3300 | H155: =E155*G155 | I155: R7 | J155: floors lvt_herringbone; M28
A156: Э11 | B156: СП-05 | C156: 5 | D156: Клей дисперсионный для LVT (0,35 кг/м²) | E156: 3 | F156: кг | G156: 450 | H156: =E156*G156 | I156: R7 | J156: P-BALC; M28
A157: Э08 | B157: СП-05 | C157: 6 | D157: Керамогранит 60×60 «светлый камень» R10 ректификат (вход) | E157: =CEILING(1.89*1.1,1.44) | F157: м² | G157: 3900 | H157: =E157*G157 | I157: R4 | J157: floors porcelain_60x60_hall; M16
A158: Э08 | B158: СП-05 | C158: 7 | D158: Керамогранит 60×60 «светлый мрамор» R10 ректификат (ванная, постирочная) | E158: =CEILING(5.85*1.1,1.44) | F158: м² | G158: 4500 | H158: =E158*G158 | I158: R5, R6 | J158: floors porcelain_60x60_bath + _laundry; M20, M25
A159: Э08 | B159: СП-05 | C159: 8 | D159: Керамогранит 60×120 «светлый мрамор» R10/B (пол душа, уклон к трапу) | E159: =CEILING(0.71*1.15,1.44) | F159: м² | G159: 5900 | H159: =E159*G159 | I159: R5 | J159: floors porcelain_60x120_shower_R10B; M20
A160: Э08 | B160: СП-05 | C160: 9 | D160: Керамогранит 60×120 «светлый мрамор» матовый — стены ванной (мокрые зоны до потолка + до +1280) и фартук кухни | E160: =CEILING(18.3*1.15,1.44) | F160: м² | G160: 5600 | H160: =E160*G160 | I160: R5, R3 | J160: walls tile_wet + tile_dry + tile_apron_porcelain; M21, M13; АР-13, АР-11
A161: Э08 | B161: СП-05 | C161: 10 | D161: Плитка «кабанчик» матовая (фартук хозмойки) | E161: =CEILING(0.77*1.1,1.0) | F161: м² | G161: 2600 | H161: =E161*G161 | I161: R6 | J161: walls tile_apron; M27; АР-14
A162: Э08 | B162: СП-05 | C162: 11 | D162: Клей плиточный C2TE S1 для ТП и крупного формата (пол 7 кг/м², стены 6 кг/м²) | E162: =CEILING((8.45*7+19.07*6)/25,1) | F162: меш. 25 кг | G162: 1250 | H162: =E162*G162 | I162: R3–R6 | J162: floors/walls tile_*
A163: Э08 | B163: СП-05 | C163: 12 | D163: Затирка эпоксидная (ванная, 0,35 кг/м²) | E163: 7 | F163: кг | G163: 1900 | H163: =E163*G163 | I163: R5 | J163: M21
A164: Э08 | B164: СП-05 | C164: 13 | D164: Затирка цементная (прихожая, постирочная, фартуки, 0,3 кг/м²) | E164: 3 | F164: кг | G164: 350 | H164: =E164*G164 | I164: R3, R4, R6 | J164: tile_*
A165: Э08 | B165: СП-05 | C165: 14 | D165: Система выравнивания плитки (СВП: клипсы, клинья) | E165: 28 | F165: м² | G165: 120 | H165: =E165*G165 | I165: R3–R6 | J165: tile_*
A166: Э08 | B166: СП-05 | C166: 15 | D166: Профиль латунь для плитки 10 мм (линия +1280 и обрамление ниш) | E166: 10.8 | F166: м | G166: 1500 | H166: =E166*G166 | I166: R5 | J166: walls tile_dry (Σ длин 5.57); ниши 3.3 м; M21
A167: Э08 | B167: СП-05 | C167: 16 | D167: Порог-ступень D3 из керамогранита 800×100×90 (изготовление) | E167: 1 | F167: шт | G167: 4500 | H167: =E167*G167 | I167: R5 | J167: J5; узел 5; D20
A168: Э08 | B168: СП-05 | C168: 17 | D168: Порог-ограничитель D4 800×80×15 (керамогранит/камень, скругл.) | E168: 1 | F168: шт | G168: 2500 | H168: =E168*G168 | I168: R6 | J168: J6; D4
A169: Э06 | B169: СП-05 | C169: 18 | D169: Гидроизоляция обмазочная 2-компонентная (2 слоя, 2,8 кг/м²; пол ванной — нижняя + основная) | E169: =CEILING(26.56*2.8,1) | F169: кг | G169: 420 | H169: =E169*G169 | I169: R5, R6 | J169: floors waterproofing_floor ×(2 в R5) + waterproofing_walls = 26.56 м²
A170: Э06 | B170: СП-05 | C170: 19 | D170: Ленты, углы, манжеты, фланец трапа (комплект на помещение) | E170: 2 | F170: компл | G170: 6500 | H170: =E170*G170 | I170: R5, R6 | J170: узел 6
A171: Э06 | B171: СП-05 | C171: 20 | D171: ЦПС М300 (подиум ванной 78,5 мм, фибра) | E171: =CEILING(5.1*0.0785*2000/40,1) | F171: меш. 40 кг | G171: 380 | H171: =E171*G171 | I171: R5 | J171: floors podium_screed_80; P-BATH
A172: Э06 | B172: СП-05 | C172: 21 | D172: Сетка Вр4 50×50 + фибра + демпферная лента (подиум, стяжка балкона) | E172: 14 | F172: м² | G172: 380 | H172: =E172*G172 | I172: R5, R7 | J172: P-BATH, P-BALC; периметры R5 9.36 м, R7 10.67 м
A173: Э06 | B173: СП-05 | C173: 22 | D173: Рамка-бортик U14 (ЦСП 20 / уголок нерж.) | E173: 1 | F173: шт | G173: 2500 | H173: =E173*G173 | I173: R5 | J173: VK-C3; J7; узел 6
A174: Э06 | B174: СП-05 | C174: 23 | D174: XPS 300 кПа 50 мм (пол балкона) | E174: 7.92 | F174: м² | G174: 650 | H174: =E174*G174 | I174: R7 | J174: floors xps50+screed55; P-BALC; D22
A175: Э06 | B175: СП-05 | C175: 24 | D175: Плёнка ПЭ 200 мкм (нахлёст 100, завод на стены) | E175: 9 | F175: м² | G175: 45 | H175: =E175*G175 | I175: R7 | J175: P-BALC
A176: Э06 | B176: СП-05 | C176: 25 | D176: ЦПС М300 (стяжка балкона 55 мм) | E176: =CEILING(6.86*0.055*2000/40,1) | F176: меш. 40 кг | G176: 380 | H176: =E176*G176 | I176: R7 | J176: P-BALC
A177: Э06 | B177: СП-05 | C177: 26 | D177: Самовыравнивающая смесь 10 мм по мату TP3 (16 кг/м²) | E177: 5 | F177: меш. 25 кг | G177: 950 | H177: =E177*G177 | I177: R7 | J177: P-BALC
A178: Э03 | B178: СП-05 | C178: 27 | D178: Остекление балкона тёплое ПВХ 70 мм, 2-камерный энергосберегающий стеклопакет, наружное стекло триплекс P2A, фурнитура с детским замком, отливы, подоконник | E178: 10.5 | F178: м² | G178: 21000 | H178: =E178*G178 | I178: R7 | J178: electrical.json balcony_heat_balance (остекление 10,5 м²); M32; №12
A179: Э03 | B179: СП-05 | C179: 28 | D179: Оконный приточный клапан в раме (гигрорегулируемый) | E179: 2 | F179: шт | G179: 3500 | H179: =E179*G179 | I179: R7 | J179: SV1, SV2; ОВ-02
A180: Э03 | B180: СП-05 | C180: 29 | D180: Утеплитель PIR 50 фольгированный (парапеты, потолок балкона) | E180: 14.4 | F180: м² | G180: 1050 | H180: =E180*G180 | I180: R7 | J180: walls gvl+paint_c6 7.05 + ceilings R7 6.08; M29, M30
A181: Э03 | B181: СП-05 | C181: 30 | D181: Лента алюминиевая, пароизоляция примыканий, пена | E181: 1 | F181: компл | G181: 4500 | H181: =E181*G181 | I181: R7 | J181: M29
A182: Э03 | B182: СП-05 | C182: 31 | D182: ГВЛ 12,5 (обшивка парапетов) 2500×1200 | E182: 3 | F182: лист | G182: 780 | H182: =E182*G182 | I182: R7 | J182: walls gvl+paint_c6
A183: Э03 | B183: СП-05 | C183: 32 | D183: Каркас для обшивки парапетов (ПП 60/27, ПН, подвесы, крепёж) | E183: 8 | F183: м² | G183: 450 | H183: =E183*G183 | I183: R7 | J183: walls gvl+paint_c6
A184: Э02 | B184: СП-05 | C184: 33 | D184: ПГП полнотелая 667×500×100 (NW1) | E184: 16 | F184: шт | G184: 520 | H184: =E184*G184 | I184: R1/R3 | J184: NW1 4.87 м²; planning.json new_walls
A185: Э02 | B185: СП-05 | C185: 34 | D185: ПГП полнотелая 667×500×80 (NW4, добор D1) | E185: 7 | F185: шт | G185: 400 | H185: =E185*G185 | I185: R2/R4, R1 | J185: NW4 1.66 м² (за вычетом проёма D2) + добор 199 0.54 м²
A186: Э02 | B186: СП-05 | C186: 35 | D186: ПГП гидрофобизированная 667×500×80 (NW8, NW9) | E186: 7 | F186: шт | G186: 450 | H186: =E186*G186 | I186: R5, R6 | J186: NW8 1.01 + NW9 1.13 м²
A187: Э02 | B187: СП-05 | C187: 36 | D187: Клей гипсовый монтажный для ПГП (2 кг/м²) + ГКЛ на клей NW1 | E187: 2 | F187: меш. 30 кг | G187: 620 | H187: =E187*G187 | I187: — | J187: new_walls
A188: Э02 | B188: СП-05 | C188: 37 | D188: Лента демпферная 10 мм + скобы/гибкие связи (без дюбелей в пол, D3) | E188: 31 | F188: м | G188: 120 | H188: =E188*G188 | I188: — | J188: new_walls: периметры NW1, NW4, NW8, NW9 = 30.18 м
... A199: Э09 | B199: СП-05 | C199: 48 | D199: HC-2: съёмная вентрешётка в низе короба CB-2 210×150 | E199: 1 | F199: шт | G199: 1800 | H199: =E199*G199 | I199: R3 | J199: HC-2; ceilings.json
A200: Э07 | B200: СП-05 | C200: 49 | D200: Штукатурка гипсовая по маякам (ср. 15 мм, 13,5 кг/м²) | E200: =CEILING(118.4*13.5/30,1) | F200: меш. 30 кг | G200: 640 | H200: =E200*G200 | I200: R1–R4, R7 | J200: walls (gross − проёмы, без каркасных облицовок) = 118.4 м²
A201: Э07 | B201: СП-05 | C201: 50 | D201: Штукатурка цементная для влажных помещений (ср. 15 мм, 18 кг/м²) | E201: =CEILING(33.89*18/25,1) | F201: меш. 25 кг | G201: 520 | H201: =E201*G201 | I201: R5, R6 | J201: walls R5, R6 = 33.89 м²
A202: Э07 | B202: СП-05 | C202: 51 | D202: Маяки 6 мм 3 м + уголки штукатурные для откосов | E202: 108 | F202: шт | G202: 70 | H202: =E202*G202 | I202: все | J202: штукатурка; откосы 16.88 м
A203: Э07 | B203: СП-05 | C203: 52 | D203: Грунт глубокого проникновения (2 прохода, 0,15 л/м²) | E203: 120 | F203: л | G203: 120 | H203: =E203*G203 | I203: все | J203: штукатурка + шпаклёвка + Q2
A204: Э07 | B204: СП-05 | C204: 53 | D204: Шпаклёвка финишная полимерная (стены Q3 1,2 кг/м², потолки Q4 1,5 кг/м², Q2 за мебелью 0,5 кг/м²) | E204: 280 | F204: кг | G204: 85 | H204: =E204*G204 | I204: все | J204: Q3 стены 105.6 + откосы 5.38 + потолки 69.3 + Q2 50.01 м²
A205: Э07 | B205: СП-05 | C205: 54 | D205: Шпаклёвка для швов ГКЛ + серпянка (0,35 кг/м²) | E205: 50 | F205: кг | G205: 70 | H205: =E205*G205 | I205: все | J205: ceilings + облицовки
A206: Э07 | B206: СП-05 | C206: 55 | D206: Стеклохолст-паутинка 45 г/м² + клей (стены под покраску) | E206: 150 | F206: м² | G206: 95 | H206: =E206*G206 | I206: все | J206: walls под окраску 105.6 м²; M05
A207: Э10 | B207: СП-05 | C207: 56 | D207: Краска акриловая матовая моющаяся (класс 1), колер C2 «лён» NCS S 1002-Y — стены, матовая моющаяся класс 1–2 | E207: =CEILING(56.72*0.11*2,1) | F207: л | G207: 1500 | H207: =E207*G207 | I207: R1, R3, R4 | J207: finish-quantities walls/ceilings; palette.json
A208: Э10 | B208: СП-05 | C208: 57 | D208: Краска износостойкая моющаяся (класс 1), колер C5 NCS S 1510-B — детская, низ до +900, износостойкая класс 1 | E208: =CEILING(9.02*0.11*2,1) | F208: л | G208: 1500 | H208: =E208*G208 | I208: R2 | J208: finish-quantities walls/ceilings; palette.json
A209: Э10 | B209: СП-05 | C209: 58 | D209: Краска акриловая глубокоматовая, колер C1 «тёплый белый» NCS S 0502-Y — детская, верх стен | E209: =CEILING(18.04*0.11*2,1) | F209: л | G209: 1400 | H209: =E209*G209 | I209: R2 | J209: finish-quantities walls/ceilings; palette.json
A210: Э10 | B210: СП-05 | C210: 59 | D210: Краска для влажных помещений матовая, колер C2 NCS S 1002-Y — стены ванной/постирочной, для влажных помещений | E210: =CEILING(11.42*0.11*2,1) | F210: л | G210: 1600 | H210: =E210*G210 | I210: R5, R6 | J210: finish-quantities walls/ceilings; palette.json
A211: Э10 | B211: СП-05 | C211: 60 | D211: Краска глубокоматовая (≤ 3 gloss), колер C6 «тёмная олива» — балкон, глубокоматовая, тёмная (3 слоя) | E211: =CEILING(10.4*0.11*3,1) | F211: л | G211: 1600 | H211: =E211*G211 | I211: R7 | J211: finish-quantities walls/ceilings; palette.json
A212: Э10 | B212: СП-05 | C212: 61 | D212: Краска акриловая глубокоматовая, колер C1 «тёплый белый» NCS S 0502-Y — откосы O2, O3, портал O4 | E212: =CEILING(5.38*0.11*2,1) | F212: л | G212: 1400 | H212: =E212*G212 | I212: R1, R2, R3 | J212: finish-quantities walls/ceilings; palette.json
A213: Э10 | B213: СП-05 | C213: 62 | D213: Краска потолочная глубокоматовая, колер C1 NCS S 0502-Y — потолки ГКЛ, глубокоматовая | E213: =CEILING(54.93*0.11*2,1) | F213: л | G213: 1300 | H213: =E213*G213 | I213: R1, R2, R3, R4 | J213: finish-quantities walls/ceilings; palette.json
A214: Э10 | B214: СП-05 | C214: 63 | D214: Краска для влажных помещений матовая, колер C1 — потолки ГКЛВ ванной и постирочной, влагостойкая | E214: =CEILING(8.29*0.11*2,1) | F214: л | G214: 1600 | H214: =E214*G214 | I214: R5, R6 | J214: finish-quantities walls/ceilings; palette.json
A215: Э10 | B215: СП-05 | C215: 64 | D215: Краска глубокоматовая (≤ 3 gloss), колер C6 «тёмная олива» — потолок балкона и ниша CN-3 | E215: =CEILING(6.08*0.11*3,1) | F215: л | G215: 1600 | H215: =E215*G215 | I215: R7 | J215: finish-quantities walls/ceilings; palette.json
A216: Э10 | B216: СП-05 | C216: 65 | D216: Карниз потолочный гладкий 80×70 полиуретан/дюрополимер | E216: =CEILING(29.33*1.1,2) | F216: м | G216: 1300 | H216: =E216*G216 | I216: R1, R3, R4 | J216: linear cornice_80 = 29.33 м
A217: Э10 | B217: СП-05 | C217: 66 | D217: Карниз потолочный 60×60 | E217: =CEILING(11.56*1.1,2) | F217: м | G217: 1000 | H217: =E217*G217 | I217: R2 | J217: linear cornice_60 = 11.56 м
A218: Э10 | B218: СП-05 | C218: 67 | D218: Карниз 40 влагостойкий (ванная) | E218: =CEILING(3.9*1.1,2) | F218: м | G218: 800 | H218: =E218*G218 | I218: R5 | J218: linear cornice_40 = 3.9 м
A219: Э10 | B219: СП-05 | C219: 68 | D219: Карниз-профиль 60 ламбрекена CB-3 | E219: =CEILING(3.58*1.1,2) | F219: м | G219: 1000 | H219: =E219*G219 | I219: R3 | J219: linear cornice_profile_lambrequin_60 = 3.58 м
A220: Э10 | B220: СП-05 | C220: 69 | D220: Карниз с LED-пазом (буазери, wall-wash) | E220: =CEILING(2.9*1.1,2) | F220: м | G220: 2800 | H220: =E220*G220 | I220: R1 | J220: linear cornice_boiserie_LED = 2.9 м
A221: Э10 | B221: СП-05 | C221: 70 | D221: Плинтус МДФ влагостойкий 120 под покраску, к стене | E221: =CEILING(30.43*1.1,2) | F221: м | G221: 850 | H221: =E221*G221 | I221: R1, R2, R3, R4 | J221: linear plinth_mdf_120 = 30.43 м
A222: Э10 | B222: СП-05 | C222: 71 | D222: Плинтус МДФ влагостойкий 80, окраска C6 | E222: =CEILING(8.21*1.1,2) | F222: м | G222: 650 | H222: =E222*G222 | I222: R7 | J222: linear plinth_mdf_80_C6 = 8.21 м
A223: Э10 | B223: СП-05 | C223: 72 | D223: Молдинг chair rail 40×20 на +900 | E223: =CEILING(10.68*1.1,2) | F223: м | G223: 650 | H223: =E223*G223 | I223: R2 | J223: linear chair_rail_40x20_at_900 = 10.68 м
A224: Э10 | B224: СП-05 | C224: 73 | D224: Молдинг 30 гладкий для рамок (R1 — рамка ТВ-зоны W7; R3 — 3 рамки на W8 [ДОПУЩЕНИЕ 900×1800]) | E224: 26 | F224: м | G224: 450 | H224: =E224*G224 | I224: R1, R3 | J224: elevations R1 W7 moulding 7.2 м; M14 рамки 16.2 м
A225: Э10 | B225: СП-05 | C225: 74 | D225: Клей монтажный для лепнины + акриловый герметик для швов | E225: 25 | F225: туба | G225: 650 | H225: =E225*G225 | I225: все | J225: погонаж Σ 123.99 м
A226: Э10 | B226: СП-05 | C226: 75 | D226: Эмаль акриловая полуматовая для погонажа и молдингов (C1/C2/C6) | E226: 7 | F226: л | G226: 1800 | H226: =E226*G226 | I226: все | J226: погонаж 123.99 м × 0,25 м² × 2 сл. × 0,1 л
A227: Э11 | B227: СП-05 | C227: 76 | D227: Т-профиль латунный 8 мм на клею (стыки J1, J2) | E227: 5.4 | F227: м | G227: 1900 | H227: =E227*G227 | I227: R3/R7, R4 | J227: counts латунный Т-профиль; J1, J2
A228: Э11 | B228: СП-05 | C228: 77 | D228: Компенсатор пробковый 5 мм (стыки J1, J2, J4) | E228: 7 | F228: м | G228: 250 | H228: =E228*G228 | I228: R1–R4, R7 | J228: floors junctions J1, J2, J4
A229: Э13 | B229: СП-05 | C229: 78 | D229: Карниз потолочный профильный 2-рядный в нише (CN-1, CN-2) | E229: 7 | F229: м | G229: 1800 | H229: =E229*G229 | I229: R1, R2 | J229: ceilings curtain_niches CN-1, CN-2 = 6.93 м
A230: Э13 | B230: СП-05 | C230: 79 | D230: П-образный потолочный карниз с электроприводом Zigbee (B1+B2+B3) | E230: 1 | F230: компл | G230: 32000 | H230: =E230*G230 | I230: R7 | J230: F37; CN-3; P-B02; M32
A231: Э13 | B231: СП-05 | C231: 80 | D231: Портьеры блэкаут + тюль-лён, пошив (спальня, окно O2) | E231: 1 | F231: компл | G231: 38000 | H231: =E231*G231 | I231: R1 | J231: M09; CN-1
...

Sheet Мебель и техника
A1: Спецификация | B1: Поз. | C1: Наименование | D1: Кол-во | E1: Ед. | F1: Цена, ₽ | G1: Сумма, ₽ | H1: Помещение | I1: Ссылка
A2: СП-02.1 | B2: 6 | C2: Стол обеденный 1800×900 (шпон дуба/массив) | D2: 1 | E2: шт | F2: 50000 | G2: =D2*F2 | H2: R3 | I2: F25
A3: СП-02.1 | B3: 7 | C3: Стул мягкий (рогожка/велюр, каркас бук) | D3: 6 | E3: шт | F3: 11000 | G3: =D3*F3 | H3: R3 | I3: F26, F27, F28, F29, F30, F31
A4: СП-02.1 | B4: 8 | C4: П-диван по размеру: спинная секция 3023×750 + 2 боковые 650×700 (отсек AV), съёмные чехлы, на ножках | D4: 1 | E4: компл | F4: 155000 | G4: =D4*F4 | H4: R7 | I4: F33, F34, F35
A5: СП-02.1 | B5: 9 | C5: Пуф-стол 500×800 | D5: 1 | E5: шт | F5: 18000 | G5: =D5*F5 | H5: R7 | I5: F36
A6: СП-02.1 | B6: 10 | C6: Кровать 1800×2000 с мягким изголовьем, рама на глайдерах | D6: 1 | E6: шт | F6: 75000 | G6: =D6*F6 | H6: R1 | I6: F42
A7: СП-02.1 | B7: 11 | C7: Матрас 1800×2000 средней жёсткости | D7: 1 | E7: шт | F7: 40000 | G7: =D7*F7 | H7: R1 | I7: F42
A8: СП-02.1 | B8: 12 | C8: Тумба прикроватная подвесная 450×500 | D8: 2 | E8: шт | F8: 9000 | G8: =D8*F8 | H8: R1 | I8: F43, F44
A9: СП-02.1 | B9: 13 | C9: ТВ-консоль подвесная 1600×300 МДФ эмаль, низ +250 | D9: 1 | E9: шт | F9: 32000 | G9: =D9*F9 | H9: R1 | I9: F47
A10: СП-02.1 | B10: 14 | C10: Стол рабочий 1400×600, столешница дуб, консоль/подстолье к стене | D10: 1 | E10: шт | F10: 35000 | G10: =D10*F10 | H10: R1 | I10: F49
A11: СП-02.1 | B11: 15 | C11: Кресло рабочее эргономичное | D11: 1 | E11: шт | F11: 18000 | G11: =D11*F11 | H11: R1 | I11: F50
A12: СП-02.1 | B12: 16 | C12: Шкаф детский 1800×600×2400, 2 секции, распашной, крепление к стене | D12: 1 | E12: шт | F12: 38000 | G12: =D12*F12 | H12: R2 | I12: F52
A13: СП-02.1 | B13: 17 | C13: Кровать детская 900×2000 с ящиками для игрушек | D13: 1 | E13: шт | F13: 28000 | G13: =D13*F13 | H13: R2 | I13: F53
... A52: СП-03.4 | B52: 31 | C52: Телевизор 65″ 4K + плоский кронштейн | D52: 1 | E52: компл | F52: 65000 | G52: =D52*F52 | H52: R1 | I52: F48; D12
C53: Итого без резерва | G53: =SUM(G2:G52)
C54: Резерв 10 % | G54: =G53*0.1
C55: ИТОГО «Мебель+техника» с резервом | G55: =G53+G54

Sheet Бюджеты
A1: Сверка с бюджетом брифа (границы бюджетов — questions.md №34)
A3: Бюджет | B3: Лимит брифа, ₽ | C3: Смета без резерва, ₽ | D3: Смета с резервом 10 %, ₽ | E3: Отклонение (с резервом), ₽ | F3: Отклонение, % | G3: Отклонение без резерва, ₽
A4: Ремонт (работы + материалы + сантехника + свет + двери + встроенные шкафы + остекление/утепление балкона) | B4: 5000000 | C4: ='Смета'!E19 | D4: ='Смета'!E22 | E4: =D4-B4 | F4: =E4/B4 | G4: =C4-B4
A5: Мебель + техника (кухня, бытовая техника, проектор/экран/акустика, ТВ, диваны, кровати, мебель детской) | B5: 1500000 | C5: ='Мебель и техника'!G53 | D5: ='Мебель и техника'!G55 | E5: =D5-B5 | F5: =E5/B5 | G5: =C5-B5
A6: ВСЕГО | B6: =SUM(B4:B5) | C6: =SUM(C4:C5) | D6: =SUM(D4:D5) | E6: =SUM(E4:E5) | F6: =E6/B6 | G6: =SUM(G4:G5)
A8: Положительное отклонение — превышение бюджета; меры — 05-estimate/value-engineering.md.

Sheet Источники и допущения
A1: Дата поиска: 2026-10-08. Сайты подрядчиков часть прайсов отдают только в выдаче (прямой доступ из среды закрыт) — цифры взяты из сниппетов поисковой выдачи и использованы как калибровка диапазона, не как точная цена.
A2: - INFOline / RBC Retail: рост цен на стройматериалы в СПб, 1-е полугодие 2026 (плитка +17,3 %, электрика +15,3 %, напольные +10,5 %, ЛКМ +10,4 %, сухие смеси +4,7 %): https://www.retail.ru/rbc/pressreleases/keramicheskaya-plitka-vnov-bet-rekord-po-rostu-tsen-v-2026-godu-otmechayut-v-infoline/
A3: - Прайсы отделочных работ СПб 2026 (покраска 450–975 ₽/м², шпаклёвка 2 сл. 495–1 155 ₽/м², плитка 800–5 500 ₽/м²): remontvspb.ru: https://remontvspb.ru/prajs/
A4: - prorabneva.ru — цены на ремонт квартир в СПб 2026: https://www.prorabneva.ru/price
A5: - len-rem.ru — расценки на отделочные работы 2026: https://len-rem.ru/rascenki-na-otdelochnye-raboty.html
A6: - remont-na5.ru — плиточные (Эконом 1 750 / Стандарт 2 800 ₽/м²) и малярные работы СПб: https://remont-na5.ru/uslugi/ukladka-plitki/
A7: - stroikaspb.com — расценки на плиточные работы СПб: https://www.stroikaspb.com/plitochnie-raboti-vspb/
A8: - hands.ru — прайс-лист на отделочные работы в СПб 2026: https://hands.ru/saint-petersburg/category/otdelka/price/
A9: - Profi.ru — установка трапов в СПб (от 1 000 ₽/шт), услуги сантехников: https://profi.ru/geo-spb/remont/santehnika/price/
A10: - Sostav.ru — рейтинг компаний и цены ремонта СПб 2026 (ориентир Москва: работы 18–35 тыс. ₽/м²): https://www.sostav.ru/blogs/286041/75556
A11: - Яндекс Карты — Coswick СПб, инженерная доска (≈ 9 000–11 100 ₽ за позицию): https://yandex.com.tr/maps/org/coswick/20770661221/prices/
A13: Допущения сметы:
... A17: - Количества — tools/gen_specs.py из слоёв 03-drawings/*.json и 04-specs/finish-quantities.json; запасы — в спецификациях.
